MANIFEST.in
README.md
setup.py
cct/__init__.py
cct.egg-info/PKG-INFO
cct.egg-info/SOURCES.txt
cct.egg-info/dependency_links.txt
cct.egg-info/entry_points.txt
cct.egg-info/not-zip-safe
cct.egg-info/requires.txt
cct.egg-info/top_level.txt
cct/core/__init__.py
cct/core/commands/__init__.py
cct/core/commands/circulator.py
cct/core/commands/command.py
cct/core/commands/detector.py
cct/core/commands/device.py
cct/core/commands/jump.py
cct/core/commands/motor.py
cct/core/commands/scan.py
cct/core/commands/script.py
cct/core/commands/transmission.py
cct/core/commands/vacuumgauge.py
cct/core/commands/xray_source.py
cct/core/devices/__init__.py
cct/core/devices/circulator.py
cct/core/devices/detector.py
cct/core/devices/motor.py
cct/core/devices/vacuumgauge.py
cct/core/devices/xray_source.py
cct/core/devices/device/__init__.py
cct/core/devices/device/device.py
cct/core/devices/device/device_modbustcp.py
cct/core/devices/device/device_tcp.py
cct/core/devices/device/exceptions.py
cct/core/instrument/__init__.py
cct/core/instrument/instrument.py
cct/core/instrument/motor.py
cct/core/instrument/privileges.py
cct/core/instrument/sample.py
cct/core/services/__init__.py
cct/core/services/accounting.py
cct/core/services/exposureanalyzer.py
cct/core/services/filesequence.py
cct/core/services/interpreter.py
cct/core/services/samples.py
cct/core/services/service.py
cct/core/services/webstate.py
cct/core/utils/__init__.py
cct/core/utils/arithmetic.py
cct/core/utils/errorvalue.py
cct/core/utils/geometrycorrections.py
cct/core/utils/io.py
cct/core/utils/pathutils.py
cct/core/utils/radint.c
cct/core/utils/radint.pyx
cct/core/utils/sascurve.py
cct/core/utils/sasimage.py
cct/core/utils/telemetry.py
cct/gui/__init__.py
cct/gui/mainwindow.py
cct/gui/accounting/__init__.py
cct/gui/accounting/projectmanager.py
cct/gui/accounting/usermanager.py
cct/gui/core/__init__.py
cct/gui/core/exposureloader.py
cct/gui/core/indicator.py
cct/gui/core/plotcurve.py
cct/gui/core/plotimage.py
cct/gui/core/scangraph.py
cct/gui/core/toolframe.py
cct/gui/core/toolwindow.py
cct/gui/devices/__init__.py
cct/gui/devices/genix.py
cct/gui/devices/haakephoenix.py
cct/gui/devices/motors.py
