Metadata-Version: 1.0
Name: cct
Version: 1.3.1
Summary: CREDO Control Tool
Home-page: http://github.com/awacha/cct
Author: Andras Wacha
Author-email: awacha@gmail.com
License: UNKNOWN
Keywords: saxs sans sas small-angle scattering x-ray instrument control
Platform: UNKNOWN
